llama_index/llms/stepfun/__init__.py
llama_index/llms/stepfun/base.py
llama_index_llms_stepfun-1.1.1.dist-info/METADATA
llama_index_llms_stepfun-1.1.1.dist-info/WHEEL
llama_index_llms_stepfun-1.1.1.dist-info/licenses/LICENSE
llama_index_llms_stepfun-1.1.1.dist-info/RECORD
