Metadata-Version: 2.4
Name: llama-index-llms-stepfun
Version: 1.1.1
Summary: llama-index llms stepfun integration
Author-email: Bestony <bestony@linux.com>
License-Expression: MIT
License-File: LICENSE
Requires-Python: <4.0,>=3.9
Requires-Dist: llama-index-core<0.15,>=0.13.0
Requires-Dist: llama-index-llms-openai-like<0.6,>=0.5.0
